README.md
setup.py
pandas_excel_view/__init__.py
pandas_excel_view.egg-info/PKG-INFO
pandas_excel_view.egg-info/SOURCES.txt
pandas_excel_view.egg-info/dependency_links.txt
pandas_excel_view.egg-info/requires.txt
pandas_excel_view.egg-info/top_level.txt