Metadata-Version: 2.1
Name: pandas-excel-view
Version: 0.0.8
Summary: Visualize Pandas DataFrames in Excel
Home-page: https://github.com/wilianzilv/pandas_excel_view
Author: Wilian Silva
Author-email: wilianzilv@gmail.com
Requires-Python: >=3.5.2
